<?xml version="1.0" encoding="utf-8"?><recording><speaker_id>53086749-205b-424c-92d1-1dc604d5419b</speaker_id><rate>16000</rate><angle>-10,0267614147894</angle><gender>male</gender><ageclass>18-20</ageclass><sentence_id>94</sentence_id><sentence>Tatsächlich ist das derzeitige Verfahren nur der letzte Abschnitt einer langen Geschichte der Annahme eines EU-Patents, die bis 1990 zurückreicht und nur von zwölf Mitgliedstaaten gefordert wurde.</sentence><cleaned_sentence>Tatsächlich ist das derzeitige Verfahren nur der letzte Abschnitt einer langen Geschichte der Annahme eines EU Patents die bis neunzehnhundertneunzig zurückreicht und nur von zwölf Mitgliedstaaten gefordert wurde</cleaned_sentence><corpus>PARL</corpus><muttersprachler>Ja</muttersprachler><bundesland>Hessen</bundesland></recording>