<?xml version="1.0" encoding="utf-8"?><recording><speaker_id>90225a4a-175a-4d3b-8b3e-9f7193518993</speaker_id><rate>16000</rate><angle>-10,0267614147894</angle><gender>male</gender><ageclass>21-30</ageclass><sentence_id>27</sentence_id><sentence> Unser Ausschuss erörtert die vorliegenden Fragen aus vielen unterschiedlichen Blickwinkeln.</sentence><cleaned_sentence>Unser Ausschuss erörtert die vorliegenden Fragen aus vielen unterschiedlichen Blickwinkeln</cleaned_sentence><corpus>PARL</corpus><muttersprachler>Ja</muttersprachler><bundesland>Hessen</bundesland></recording>