<?xml version="1.0" encoding="utf-8"?><recording><speaker_id>78421124-2319-4cf1-b3d3-4f95b3001cee</speaker_id><rate>16000</rate><angle>-10,0267614147894</angle><gender>male</gender><ageclass>21-30</ageclass><sentence_id>217</sentence_id><sentence>Zweitens stimme ich dem zu, was ich hier bereits von einem Kollegen über die Thematik der Inseln gehört habe, und ich möchte ebenfalls auf die Gebiete in äußerster Randlage aufmerksam machen.</sentence><cleaned_sentence>Zweitens stimme ich dem zu was ich hier bereits von einem Kollegen über die Thematik der Inseln gehört habe und ich möchte ebenfalls auf die Gebiete in äußerster Randlage aufmerksam machen</cleaned_sentence><corpus>PARL</corpus><muttersprachler>Ja</muttersprachler><bundesland>Hessen</bundesland></recording>